faropt/__init__.py
faropt/templates/__init__.py
faropt/templates/blackbox.py
faropt/templates/opsplan.py
faropt/templates/routing.py
faropt-0.2.21.dist-info/METADATA
faropt-0.2.21.dist-info/WHEEL
faropt-0.2.21.dist-info/top_level.txt
faropt-0.2.21.dist-info/RECORD
