Metadata-Version: 2.1
Name: faropt
Version: 0.2.21
Summary: Fargate based Numerical Optimization Template
Home-page: https://github.com/aws-samples/faropt
Author: Shreyas Subramanian
Author-email: subshrey@amazon.com
License: MIT
Platform: UNKNOWN
Classifier: Development Status :: 3 - Alpha
Classifier: Intended Audience :: Developers
Classifier: Natural Language :: English
Classifier: License :: OSI Approved :: Apache Software License
Classifier: Programming Language :: Python
Requires-Dist: boto3
Provides-Extra: async
Requires-Dist: scikit-optimize ; extra == 'async'
